businessmessages/__init__.py
businessmessages/businessmessages_v1_client.py
businessmessages/businessmessages_v1_messages.py
google_businessmessages-1.0.5.dist-info/LICENSE
google_businessmessages-1.0.5.dist-info/METADATA
google_businessmessages-1.0.5.dist-info/WHEEL
google_businessmessages-1.0.5.dist-info/top_level.txt
google_businessmessages-1.0.5.dist-info/RECORD
