Metadata-Version: 2.1
Name: google-businessmessages
Version: 1.0.5
Summary: Google's Business Messages API client library
Home-page: https://github.com/google-business-communications/python-businessmessages
Author: Google LLC
Author-email: googleapis-packages@google.com
License: Apache 2.0
Platform: UNKNOWN
Classifier: Programming Language :: Python :: 3
Classifier: Intended Audience :: Developers
Classifier: License :: OSI Approved :: Apache Software License
Classifier: Operating System :: OS Independent
Requires-Python: >=3.6
License-File: LICENSE
